Workbook

Sheet INVENTARIO
A1: INVENTARIO ÉTOILE
A3: CODIGO | B3: PRENDA | C3: COLOR | D3: TALLA | E3: PRECIO | F3: STOCK
A4: BLEL-VI-S | B4: Blusa Eliana | C4: Vino | D4: S | E4: 8 | F4: 0
A5: BLEL-VI-M | B5: Blusa Eliana | C5: Vino | D5: M | E5: 8 | F5: 0
A6: BLAN-NE-S | B6: Blusa Ana | C6: Negro | D6: S | E6: 6 | F6: 98
A7: BLAN-NE-M | B7: Blusa Ana | C7: Negro | D7: M | E7: 6 | F7: 99
A8: BLAN-RO-S | B8: Blusa Ana | C8: Palo de Rosa | D8: S | E8: 6 | F8: 98
A9: BLAN-RO-M | B9: Blusa Ana | C9: Palo de Rosa | D9: M | E9: 6 | F9: 98
A10: BLAN-BC-S | B10: Blusa Ana | C10: Blanco | D10: S | E10: 6 | F10: 0
A11: BLAN-BC-M | B11: Blusa Ana | C11: Blanco | D11: M | E11: 6 | F11: 0
A12: BLKC-RO-S | B12: Blusa Kaila Crop | C12: Rosa Pastel | D12: S | E12: 6 | F12: 0
A13: BLKC-RO-M | B13: Blusa Kaila Crop | C13: Rosa Pastel | D13: M | E13: 6 | F13: 0
A14: BLNH-NE-S | B14: Blusa Naho | C14: Negro | D14: S | E14: 8 | F14: 0
A15: BLNH-NE-M | B15: Blusa Naho | C15: Negro | D15: M | E15: 8 | F15: 0
... A74: BDVL-LP-M | B74: Body Valeska | C74: Leopardo | D74: M | E74: 10 | F74: 0
A75: BLOB-NE-S | F75: 0
A76: BLOB-NE-M | F76: 0
A77: BLOB-RO-S | F77: 0
A78: BLOB-RO-M | F78: 0
A79: BLOB-BL-S | F79: 0
A80: BLOB-BL-M | F80: 0
A81: BLEC-NE-S | F81: 0
A82: BLEC-NE-M | F82: 0
A83: BLEC-BL-S | F83: 0
A84: BLEC-BL-M | F84: 0
A85: BLEC-RO-S | F85: 0
A86: BLEC-RO-M | F86: 0
... A107: BLCH-RSP-M | F107: 0

Sheet VENTAS
A1: PEDIDO / VENTA ÉTOILE
A3: Nombre del cliente: | D3: Teléfono:
A5: CODIGO | B5: PRENDA | C5: COLOR | D5: TALLA | E5: PRECIO | F5: CANT | G5: SUBTOTAL
B6: =IF(A6="","",IFERROR(INDEX(INVENTARIO!$B:$B,MATCH(A6,INVENTARIO!$A:$A,0)),"No encontrado")) | C6: =IF(A6="","",IFERROR(INDEX(INVENTARIO!$C:$C,MATCH(A6,INVENTARIO!$A:$A,0)),"")) | D6: =IF(A6="","",IFERROR(INDEX(INVENTARIO!$D:$D,MATCH(A6,INVENTARIO!$A:$A,0)),"")) | E6: =IF(A6="","",IFERROR(INDEX(INVENTARIO!$E:$E,MATCH(A6,INVENTARIO!$A:$A,0)),"")) | G6: =IF(A6="","",E6*F6)
B7: =IF(A7="","",IFERROR(INDEX(INVENTARIO!$B:$B,MATCH(A7,INVENTARIO!$A:$A,0)),"No encontrado")) | C7: =IF(A7="","",IFERROR(INDEX(INVENTARIO!$C:$C,MATCH(A7,INVENTARIO!$A:$A,0)),"")) | D7: =IF(A7="","",IFERROR(INDEX(INVENTARIO!$D:$D,MATCH(A7,INVENTARIO!$A:$A,0)),"")) | E7: =IF(A7="","",IFERROR(INDEX(INVENTARIO!$F:$F,MATCH(A7,INVENTARIO!$A:$A,0)),"")) | G7: =IF(A7="","",E7*F7)
B8: =IF(A8="","",IFERROR(INDEX(INVENTARIO!$B:$B,MATCH(A8,INVENTARIO!$A:$A,0)),"No encontrado")) | C8: =IF(A8="","",IFERROR(INDEX(INVENTARIO!$C:$C,MATCH(A8,INVENTARIO!$A:$A,0)),"")) | D8: =IF(A8="","",IFERROR(INDEX(INVENTARIO!$D:$D,MATCH(A8,INVENTARIO!$A:$A,0)),"")) | E8: =IF(A8="","",IFERROR(INDEX(INVENTARIO!$F:$F,MATCH(A8,INVENTARIO!$A:$A,0)),"")) | G8: =IF(A8="","",E8*F8)
B9: =IF(A9="","",IFERROR(INDEX(INVENTARIO!$B:$B,MATCH(A9,INVENTARIO!$A:$A,0)),"No encontrado")) | C9: =IF(A9="","",IFERROR(INDEX(INVENTARIO!$C:$C,MATCH(A9,INVENTARIO!$A:$A,0)),"")) | D9: =IF(A9="","",IFERROR(INDEX(INVENTARIO!$D:$D,MATCH(A9,INVENTARIO!$A:$A,0)),"")) | E9: =IF(A9="","",IFERROR(INDEX(INVENTARIO!$F:$F,MATCH(A9,INVENTARIO!$A:$A,0)),"")) | G9: =IF(A9="","",E9*F9)
B10: =IF(A10="","",IFERROR(INDEX(INVENTARIO!$B:$B,MATCH(A10,INVENTARIO!$A:$A,0)),"No encontrado")) | C10: =IF(A10="","",IFERROR(INDEX(INVENTARIO!$C:$C,MATCH(A10,INVENTARIO!$A:$A,0)),"")) | D10: =IF(A10="","",IFERROR(INDEX(INVENTARIO!$D:$D,MATCH(A10,INVENTARIO!$A:$A,0)),"")) | E10: =IF(A10="","",IFERROR(INDEX(INVENTARIO!$F:$F,MATCH(A10,INVENTARIO!$A:$A,0)),"")) | G10: =IF(A10="","",E10*F10)
B11: =IF(A11="","",IFERROR(INDEX(INVENTARIO!$B:$B,MATCH(A11,INVENTARIO!$A:$A,0)),"No encontrado")) | C11: =IF(A11="","",IFERROR(INDEX(INVENTARIO!$C:$C,MATCH(A11,INVENTARIO!$A:$A,0)),"")) | D11: =IF(A11="","",IFERROR(INDEX(INVENTARIO!$D:$D,MATCH(A11,INVENTARIO!$A:$A,0)),"")) | E11: =IF(A11="","",IFERROR(INDEX(INVENTARIO!$F:$F,MATCH(A11,INVENTARIO!$A:$A,0)),"")) | G11: =IF(A11="","",E11*F11)
B12: =IF(A12="","",IFERROR(INDEX(INVENTARIO!$B:$B,MATCH(A12,INVENTARIO!$A:$A,0)),"No encontrado")) | C12: =IF(A12="","",IFERROR(INDEX(INVENTARIO!$C:$C,MATCH(A12,INVENTARIO!$A:$A,0)),"")) | D12: =IF(A12="","",IFERROR(INDEX(INVENTARIO!$D:$D,MATCH(A12,INVENTARIO!$A:$A,0)),"")) | E12: =IF(A12="","",IFERROR(INDEX(INVENTARIO!$F:$F,MATCH(A12,INVENTARIO!$A:$A,0)),"")) | G12: =IF(A12="","",E12*F12)
B13: =IF(A13="","",IFERROR(INDEX(INVENTARIO!$B:$B,MATCH(A13,INVENTARIO!$A:$A,0)),"No encontrado")) | C13: =IF(A13="","",IFERROR(INDEX(INVENTARIO!$C:$C,MATCH(A13,INVENTARIO!$A:$A,0)),"")) | D13: =IF(A13="","",IFERROR(INDEX(INVENTARIO!$D:$D,MATCH(A13,INVENTARIO!$A:$A,0)),"")) | E13: =IF(A13="","",IFERROR(INDEX(INVENTARIO!$F:$F,MATCH(A13,INVENTARIO!$A:$A,0)),"")) | G13: =IF(A13="","",E13*F13)
B14: =IF(A14="","",IFERROR(INDEX(INVENTARIO!$B:$B,MATCH(A14,INVENTARIO!$A:$A,0)),"No encontrado")) | C14: =IF(A14="","",IFERROR(INDEX(INVENTARIO!$C:$C,MATCH(A14,INVENTARIO!$A:$A,0)),"")) | D14: =IF(A14="","",IFERROR(INDEX(INVENTARIO!$D:$D,MATCH(A14,INVENTARIO!$A:$A,0)),"")) | E14: =IF(A14="","",IFERROR(INDEX(INVENTARIO!$F:$F,MATCH(A14,INVENTARIO!$A:$A,0)),"")) | G14: =IF(A14="","",E14*F14)
B15: =IF(A15="","",IFERROR(INDEX(INVENTARIO!$B:$B,MATCH(A15,INVENTARIO!$A:$A,0)),"No encontrado")) | C15: =IF(A15="","",IFERROR(INDEX(INVENTARIO!$C:$C,MATCH(A15,INVENTARIO!$A:$A,0)),"")) | D15: =IF(A15="","",IFERROR(INDEX(INVENTARIO!$D:$D,MATCH(A15,INVENTARIO!$A:$A,0)),"")) | E15: =IF(A15="","",IFERROR(INDEX(INVENTARIO!$F:$F,MATCH(A15,INVENTARIO!$A:$A,0)),"")) | G15: =IF(A15="","",E15*F15)
B16: =IF(A16="","",IFERROR(INDEX(INVENTARIO!$B:$B,MATCH(A16,INVENTARIO!$A:$A,0)),"No encontrado")) | C16: =IF(A16="","",IFERROR(INDEX(INVENTARIO!$C:$C,MATCH(A16,INVENTARIO!$A:$A,0)),"")) | D16: =IF(A16="","",IFERROR(INDEX(INVENTARIO!$D:$D,MATCH(A16,INVENTARIO!$A:$A,0)),"")) | E16: =IF(A16="","",IFERROR(INDEX(INVENTARIO!$F:$F,MATCH(A16,INVENTARIO!$A:$A,0)),"")) | G16: =IF(A16="","",E16*F16)
B17: =IF(A17="","",IFERROR(INDEX(INVENTARIO!$B:$B,MATCH(A17,INVENTARIO!$A:$A,0)),"No encontrado")) | C17: =IF(A17="","",IFERROR(INDEX(INVENTARIO!$C:$C,MATCH(A17,INVENTARIO!$A:$A,0)),"")) | D17: =IF(A17="","",IFERROR(INDEX(INVENTARIO!$D:$D,MATCH(A17,INVENTARIO!$A:$A,0)),"")) | E17: =IF(A17="","",IFERROR(INDEX(INVENTARIO!$F:$F,MATCH(A17,INVENTARIO!$A:$A,0)),"")) | G17: =IF(A17="","",E17*F17)
B18: =IF(A18="","",IFERROR(INDEX(INVENTARIO!$B:$B,MATCH(A18,INVENTARIO!$A:$A,0)),"No encontrado")) | C18: =IF(A18="","",IFERROR(INDEX(INVENTARIO!$C:$C,MATCH(A18,INVENTARIO!$A:$A,0)),"")) | D18: =IF(A18="","",IFERROR(INDEX(INVENTARIO!$D:$D,MATCH(A18,INVENTARIO!$A:$A,0)),"")) | E18: =IF(A18="","",IFERROR(INDEX(INVENTARIO!$F:$F,MATCH(A18,INVENTARIO!$A:$A,0)),"")) | G18: =IF(A18="","",E18*F18)
... B20: =IF(A20="","",IFERROR(INDEX(INVENTARIO!$B:$B,MATCH(A20,INVENTARIO!$A:$A,0)),"No encontrado")) | C20: =IF(A20="","",IFERROR(INDEX(INVENTARIO!$C:$C,MATCH(A20,INVENTARIO!$A:$A,0)),"")) | D20: =IF(A20="","",IFERROR(INDEX(INVENTARIO!$D:$D,MATCH(A20,INVENTARIO!$A:$A,0)),"")) | E20: =IF(A20="","",IFERROR(INDEX(INVENTARIO!$F:$F,MATCH(A20,INVENTARIO!$A:$A,0)),"")) | G20: =IF(A20="","",E20*F20)
A22: TOTAL | G22: =SUM(G6:G20)
A23: DESCUENTO % | B23: 10
A24: MONTO DESCUENTO | G24: =G22*B23/100
A25: TOTAL CON DESCUENTO | G25: =G22-G24
A27: Instrucciones: escribe el CODIGO (hoja INVENTARIO) en la columna A y la cantidad en F. Todo lo demás se llena solo.

Sheet HISTORIAL
A1: HISTORIAL DE VENTAS ÉTOILE
A2: Registra aquí cada venta CONFIRMADA (una fila por prenda vendida). Esto alimenta el STOCK DISPONIBLE en INVENTARIO.
A4: FECHA | B4: CODIGO | C4: PRENDA | D4: COLOR | E4: TALLA | F4: CANT | G4: PRECIO | H4: SUBTOTAL | I4: CLIENTE | J4: PEDIDO_ID | K4: TELEFONO | L4: METODO_PAGO | M4: NUM_TRANSACCION
C6: =IF(B6="","",IFERROR(INDEX(INVENTARIO!$B:$B,MATCH(B6,INVENTARIO!$A:$A,0)),"No encontrado")) | D6: =IF(B6="","",IFERROR(INDEX(INVENTARIO!$C:$C,MATCH(B6,INVENTARIO!$A:$A,0)),"")) | E6: =IF(B6="","",IFERROR(INDEX(INVENTARIO!$D:$D,MATCH(B6,INVENTARIO!$A:$A,0)),"")) | G6: =IF(B6="","",IFERROR(INDEX(INVENTARIO!$F:$F,MATCH(B6,INVENTARIO!$A:$A,0)),"")) | H6: =IF(B6="","",G6*F6)
C7: =IF(B7="","",IFERROR(INDEX(INVENTARIO!$B:$B,MATCH(B7,INVENTARIO!$A:$A,0)),"No encontrado")) | D7: =IF(B7="","",IFERROR(INDEX(INVENTARIO!$C:$C,MATCH(B7,INVENTARIO!$A:$A,0)),"")) | E7: =IF(B7="","",IFERROR(INDEX(INVENTARIO!$D:$D,MATCH(B7,INVENTARIO!$A:$A,0)),"")) | G7: =IF(B7="","",IFERROR(INDEX(INVENTARIO!$F:$F,MATCH(B7,INVENTARIO!$A:$A,0)),"")) | H7: =IF(B7="","",G7*F7)
C8: =IF(B8="","",IFERROR(INDEX(INVENTARIO!$B:$B,MATCH(B8,INVENTARIO!$A:$A,0)),"No encontrado")) | D8: =IF(B8="","",IFERROR(INDEX(INVENTARIO!$C:$C,MATCH(B8,INVENTARIO!$A:$A,0)),"")) | E8: =IF(B8="","",IFERROR(INDEX(INVENTARIO!$D:$D,MATCH(B8,INVENTARIO!$A:$A,0)),"")) | G8: =IF(B8="","",IFERROR(INDEX(INVENTARIO!$F:$F,MATCH(B8,INVENTARIO!$A:$A,0)),"")) | H8: =IF(B8="","",G8*F8)
C9: =IF(B9="","",IFERROR(INDEX(INVENTARIO!$B:$B,MATCH(B9,INVENTARIO!$A:$A,0)),"No encontrado")) | D9: =IF(B9="","",IFERROR(INDEX(INVENTARIO!$C:$C,MATCH(B9,INVENTARIO!$A:$A,0)),"")) | E9: =IF(B9="","",IFERROR(INDEX(INVENTARIO!$D:$D,MATCH(B9,INVENTARIO!$A:$A,0)),"")) | G9: =IF(B9="","",IFERROR(INDEX(INVENTARIO!$F:$F,MATCH(B9,INVENTARIO!$A:$A,0)),"")) | H9: =IF(B9="","",G9*F9)
C10: =IF(B10="","",IFERROR(INDEX(INVENTARIO!$B:$B,MATCH(B10,INVENTARIO!$A:$A,0)),"No encontrado")) | D10: =IF(B10="","",IFERROR(INDEX(INVENTARIO!$C:$C,MATCH(B10,INVENTARIO!$A:$A,0)),"")) | E10: =IF(B10="","",IFERROR(INDEX(INVENTARIO!$D:$D,MATCH(B10,INVENTARIO!$A:$A,0)),"")) | G10: =IF(B10="","",IFERROR(INDEX(INVENTARIO!$F:$F,MATCH(B10,INVENTARIO!$A:$A,0)),"")) | H10: =IF(B10="","",G10*F10)
C11: =IF(B11="","",IFERROR(INDEX(INVENTARIO!$B:$B,MATCH(B11,INVENTARIO!$A:$A,0)),"No encontrado")) | D11: =IF(B11="","",IFERROR(INDEX(INVENTARIO!$C:$C,MATCH(B11,INVENTARIO!$A:$A,0)),"")) | E11: =IF(B11="","",IFERROR(INDEX(INVENTARIO!$D:$D,MATCH(B11,INVENTARIO!$A:$A,0)),"")) | G11: =IF(B11="","",IFERROR(INDEX(INVENTARIO!$F:$F,MATCH(B11,INVENTARIO!$A:$A,0)),"")) | H11: =IF(B11="","",G11*F11)
C12: =IF(B12="","",IFERROR(INDEX(INVENTARIO!$B:$B,MATCH(B12,INVENTARIO!$A:$A,0)),"No encontrado")) | D12: =IF(B12="","",IFERROR(INDEX(INVENTARIO!$C:$C,MATCH(B12,INVENTARIO!$A:$A,0)),"")) | E12: =IF(B12="","",IFERROR(INDEX(INVENTARIO!$D:$D,MATCH(B12,INVENTARIO!$A:$A,0)),"")) | G12: =IF(B12="","",IFERROR(INDEX(INVENTARIO!$F:$F,MATCH(B12,INVENTARIO!$A:$A,0)),"")) | H12: =IF(B12="","",G12*F12)
C13: =IF(B13="","",IFERROR(INDEX(INVENTARIO!$B:$B,MATCH(B13,INVENTARIO!$A:$A,0)),"No encontrado")) | D13: =IF(B13="","",IFERROR(INDEX(INVENTARIO!$C:$C,MATCH(B13,INVENTARIO!$A:$A,0)),"")) | E13: =IF(B13="","",IFERROR(INDEX(INVENTARIO!$D:$D,MATCH(B13,INVENTARIO!$A:$A,0)),"")) | G13: =IF(B13="","",IFERROR(INDEX(INVENTARIO!$F:$F,MATCH(B13,INVENTARIO!$A:$A,0)),"")) | H13: =IF(B13="","",G13*F13)
C14: =IF(B14="","",IFERROR(INDEX(INVENTARIO!$B:$B,MATCH(B14,INVENTARIO!$A:$A,0)),"No encontrado")) | D14: =IF(B14="","",IFERROR(INDEX(INVENTARIO!$C:$C,MATCH(B14,INVENTARIO!$A:$A,0)),"")) | E14: =IF(B14="","",IFERROR(INDEX(INVENTARIO!$D:$D,MATCH(B14,INVENTARIO!$A:$A,0)),"")) | G14: =IF(B14="","",IFERROR(INDEX(INVENTARIO!$F:$F,MATCH(B14,INVENTARIO!$A:$A,0)),"")) | H14: =IF(B14="","",G14*F14)
C15: =IF(B15="","",IFERROR(INDEX(INVENTARIO!$B:$B,MATCH(B15,INVENTARIO!$A:$A,0)),"No encontrado")) | D15: =IF(B15="","",IFERROR(INDEX(INVENTARIO!$C:$C,MATCH(B15,INVENTARIO!$A:$A,0)),"")) | E15: =IF(B15="","",IFERROR(INDEX(INVENTARIO!$D:$D,MATCH(B15,INVENTARIO!$A:$A,0)),"")) | G15: =IF(B15="","",IFERROR(INDEX(INVENTARIO!$F:$F,MATCH(B15,INVENTARIO!$A:$A,0)),"")) | H15: =IF(B15="","",G15*F15)
C16: =IF(B16="","",IFERROR(INDEX(INVENTARIO!$B:$B,MATCH(B16,INVENTARIO!$A:$A,0)),"No encontrado")) | D16: =IF(B16="","",IFERROR(INDEX(INVENTARIO!$C:$C,MATCH(B16,INVENTARIO!$A:$A,0)),"")) | E16: =IF(B16="","",IFERROR(INDEX(INVENTARIO!$D:$D,MATCH(B16,INVENTARIO!$A:$A,0)),"")) | G16: =IF(B16="","",IFERROR(INDEX(INVENTARIO!$F:$F,MATCH(B16,INVENTARIO!$A:$A,0)),"")) | H16: =IF(B16="","",G16*F16)
C17: =IF(B17="","",IFERROR(INDEX(INVENTARIO!$B:$B,MATCH(B17,INVENTARIO!$A:$A,0)),"No encontrado")) | D17: =IF(B17="","",IFERROR(INDEX(INVENTARIO!$C:$C,MATCH(B17,INVENTARIO!$A:$A,0)),"")) | E17: =IF(B17="","",IFERROR(INDEX(INVENTARIO!$D:$D,MATCH(B17,INVENTARIO!$A:$A,0)),"")) | G17: =IF(B17="","",IFERROR(INDEX(INVENTARIO!$F:$F,MATCH(B17,INVENTARIO!$A:$A,0)),"")) | H17: =IF(B17="","",G17*F17)
... C204: =IF(B204="","",IFERROR(INDEX(INVENTARIO!$B:$B,MATCH(B204,INVENTARIO!$A:$A,0)),"No encontrado")) | D204: =IF(B204="","",IFERROR(INDEX(INVENTARIO!$C:$C,MATCH(B204,INVENTARIO!$A:$A,0)),"")) | E204: =IF(B204="","",IFERROR(INDEX(INVENTARIO!$D:$D,MATCH(B204,INVENTARIO!$A:$A,0)),"")) | G204: =IF(B204="","",IFERROR(INDEX(INVENTARIO!$F:$F,MATCH(B204,INVENTARIO!$A:$A,0)),"")) | H204: =IF(B204="","",G204*F204)
A206: TOTAL VENDIDO (todo el historial) | H206: =SUM(H5:H204)
A208: Instrucciones: cada vez que cierres una venta, agrega una fila aquí con fecha, código y cantidad. Lo demás se llena solo.
A211: RESUMEN: CUÁNTO SE HA VENDIDO DE CADA PRENDA
A212: CODIGO | B212: PRENDA | C212: CANTIDAD VENDIDA | D212: TOTAL EN $
A213: =IF(INVENTARIO!A4="","",INVENTARIO!A4) | B213: =IF(INVENTARIO!A4="","",INVENTARIO!B4&" - "&INVENTARIO!C4&" "&INVENTARIO!D4) | C213: =IF(INVENTARIO!A4="","",SUMIFS($F$5:$F$204,$B$5:$B$204,INVENTARIO!A4)) | D213: =IF(INVENTARIO!A4="","",SUMIFS($H$5:$H$204,$B$5:$B$204,INVENTARIO!A4))
A214: =IF(INVENTARIO!A5="","",INVENTARIO!A5) | B214: =IF(INVENTARIO!A5="","",INVENTARIO!B5&" - "&INVENTARIO!C5&" "&INVENTARIO!D5) | C214: =IF(INVENTARIO!A5="","",SUMIFS($F$5:$F$204,$B$5:$B$204,INVENTARIO!A5)) | D214: =IF(INVENTARIO!A5="","",SUMIFS($H$5:$H$204,$B$5:$B$204,INVENTARIO!A5))
A215: =IF(INVENTARIO!A6="","",INVENTARIO!A6) | B215: =IF(INVENTARIO!A6="","",INVENTARIO!B6&" - "&INVENTARIO!C6&" "&INVENTARIO!D6) | C215: =IF(INVENTARIO!A6="","",SUMIFS($F$5:$F$204,$B$5:$B$204,INVENTARIO!A6)) | D215: =IF(INVENTARIO!A6="","",SUMIFS($H$5:$H$204,$B$5:$B$204,INVENTARIO!A6))
A216: =IF(INVENTARIO!A7="","",INVENTARIO!A7) | B216: =IF(INVENTARIO!A7="","",INVENTARIO!B7&" - "&INVENTARIO!C7&" "&INVENTARIO!D7) | C216: =IF(INVENTARIO!A7="","",SUMIFS($F$5:$F$204,$B$5:$B$204,INVENTARIO!A7)) | D216: =IF(INVENTARIO!A7="","",SUMIFS($H$5:$H$204,$B$5:$B$204,INVENTARIO!A7))
A217: =IF(INVENTARIO!A8="","",INVENTARIO!A8) | B217: =IF(INVENTARIO!A8="","",INVENTARIO!B8&" - "&INVENTARIO!C8&" "&INVENTARIO!D8) | C217: =IF(INVENTARIO!A8="","",SUMIFS($F$5:$F$204,$B$5:$B$204,INVENTARIO!A8)) | D217: =IF(INVENTARIO!A8="","",SUMIFS($H$5:$H$204,$B$5:$B$204,INVENTARIO!A8))
A218: =IF(INVENTARIO!A9="","",INVENTARIO!A9) | B218: =IF(INVENTARIO!A9="","",INVENTARIO!B9&" - "&INVENTARIO!C9&" "&INVENTARIO!D9) | C218: =IF(INVENTARIO!A9="","",SUMIFS($F$5:$F$204,$B$5:$B$204,INVENTARIO!A9)) | D218: =IF(INVENTARIO!A9="","",SUMIFS($H$5:$H$204,$B$5:$B$204,INVENTARIO!A9))
A219: =IF(INVENTARIO!A10="","",INVENTARIO!A10) | B219: =IF(INVENTARIO!A10="","",INVENTARIO!B10&" - "&INVENTARIO!C10&" "&INVENTARIO!D10) | C219: =IF(INVENTARIO!A10="","",SUMIFS($F$5:$F$204,$B$5:$B$204,INVENTARIO!A10)) | D219: =IF(INVENTARIO!A10="","",SUMIFS($H$5:$H$204,$B$5:$B$204,INVENTARIO!A10))
A220: =IF(INVENTARIO!A11="","",INVENTARIO!A11) | B220: =IF(INVENTARIO!A11="","",INVENTARIO!B11&" - "&INVENTARIO!C11&" "&INVENTARIO!D11) | C220: =IF(INVENTARIO!A11="","",SUMIFS($F$5:$F$204,$B$5:$B$204,INVENTARIO!A11)) | D220: =IF(INVENTARIO!A11="","",SUMIFS($H$5:$H$204,$B$5:$B$204,INVENTARIO!A11))
A221: =IF(INVENTARIO!A12="","",INVENTARIO!A12) | B221: =IF(INVENTARIO!A12="","",INVENTARIO!B12&" - "&INVENTARIO!C12&" "&INVENTARIO!D12) | C221: =IF(INVENTARIO!A12="","",SUMIFS($F$5:$F$204,$B$5:$B$204,INVENTARIO!A12)) | D221: =IF(INVENTARIO!A12="","",SUMIFS($H$5:$H$204,$B$5:$B$204,INVENTARIO!A12))
A222: =IF(INVENTARIO!A13="","",INVENTARIO!A13) | B222: =IF(INVENTARIO!A13="","",INVENTARIO!B13&" - "&INVENTARIO!C13&" "&INVENTARIO!D13) | C222: =IF(INVENTARIO!A13="","",SUMIFS($F$5:$F$204,$B$5:$B$204,INVENTARIO!A13)) | D222: =IF(INVENTARIO!A13="","",SUMIFS($H$5:$H$204,$B$5:$B$204,INVENTARIO!A13))
A223: =IF(INVENTARIO!A14="","",INVENTARIO!A14) | B223: =IF(INVENTARIO!A14="","",INVENTARIO!B14&" - "&INVENTARIO!C14&" "&INVENTARIO!D14) | C223: =IF(INVENTARIO!A14="","",SUMIFS($F$5:$F$204,$B$5:$B$204,INVENTARIO!A14)) | D223: =IF(INVENTARIO!A14="","",SUMIFS($H$5:$H$204,$B$5:$B$204,INVENTARIO!A14))
A224: =IF(INVENTARIO!A15="","",INVENTARIO!A15) | B224: =IF(INVENTARIO!A15="","",INVENTARIO!B15&" - "&INVENTARIO!C15&" "&INVENTARIO!D15) | C224: =IF(INVENTARIO!A15="","",SUMIFS($F$5:$F$204,$B$5:$B$204,INVENTARIO!A15)) | D224: =IF(INVENTARIO!A15="","",SUMIFS($H$5:$H$204,$B$5:$B$204,INVENTARIO!A15))
... A238: =IF(INVENTARIO!A29="","",INVENTARIO!A29) | B238: =IF(INVENTARIO!A29="","",INVENTARIO!B29&" - "&INVENTARIO!C29&" "&INVENTARIO!D29) | C238: =IF(INVENTARIO!A29="","",SUMIFS($F$5:$F$204,$B$5:$B$204,INVENTARIO!A29)) | D238: =IF(INVENTARIO!A29="","",SUMIFS($H$5:$H$204,$B$5:$B$204,INVENTARIO!A29))
A239: =IF(INVENTARIO!A118="","",INVENTARIO!A118) | B239: =IF(INVENTARIO!A118="","",INVENTARIO!B118&" - "&INVENTARIO!C118&" "&INVENTARIO!D118) | C239: =IF(INVENTARIO!A118="","",SUMIFS($F$5:$F$204,$B$5:$B$204,INVENTARIO!A118)) | D239: =IF(INVENTARIO!A118="","",SUMIFS($H$5:$H$204,$B$5:$B$204,INVENTARIO!A118))
A241: Este resumen se actualiza solo. Ordénalo de mayor a menor en "CANTIDAD VENDIDA" para ver qué prendas cortar de nuevo.
